qe_api_client/__init__.py
qe_api_client/engine.py
qe_api_client/engine_communicator.py
qe_api_client/structs.py
qe_api_client/api_classes/__init__.py
qe_api_client/api_classes/engine_app_api.py
qe_api_client/api_classes/engine_field_api.py
qe_api_client/api_classes/engine_generic_dimension_api.py
qe_api_client/api_classes/engine_generic_measure_api.py
qe_api_client/api_classes/engine_generic_object_api.py
qe_api_client/api_classes/engine_generic_variable_api.py
qe_api_client/api_classes/engine_global_api.py
qe_api_client-3.0.0.dist-info/licenses/LICENSE
qe_api_client-3.0.0.dist-info/METADATA
qe_api_client-3.0.0.dist-info/WHEEL
qe_api_client-3.0.0.dist-info/top_level.txt
qe_api_client-3.0.0.dist-info/RECORD
