Metadata-Version: 2.4
Name: qe-api-client
Version: 3.0.0
Summary: Python client for the Qlik Engine JSON API
Home-page: https://github.com/lr-bicc/qe-api-client
Author: Rumen Vasilev
Author-email: R.Vasilev@LRWorld.com
Classifier: Programming Language :: Python :: 3
Classifier: License :: OSI Approved :: MIT License
Classifier: Operating System :: OS Independent
Requires-Python: >=3.6
License-File: LICENSE
Requires-Dist: websocket-client>=1.0.0
Requires-Dist: pandas>=2.2.0
Requires-Dist: numpy>=2.0.0
Requires-Dist: uuid>=1.0
Dynamic: author
Dynamic: author-email
Dynamic: classifier
Dynamic: description
Dynamic: description-content-type
Dynamic: home-page
Dynamic: license-file
Dynamic: requires-dist
Dynamic: requires-python
Dynamic: summary
